potion/__init__.py
potion/const.py
potion/api/__init__.py
potion/api/delete.py
potion/api/get.py
potion/api/patch.py
potion/api/post.py
potion/backup/__init__.py
potion/backup/__main__.py
potion/beans/__init__.py
potion/beans/base.py
potion/beans/database.py
potion/beans/page.py
potion/objects/__init__.py
potion/objects/block.py
potion/objects/common.py
potion/objects/database.py
potion/objects/embeds.py
potion/objects/emoji.py
potion/objects/enums.py
potion/objects/error.py
potion/objects/file.py
potion/objects/page.py
potion/objects/pagination.py
potion/objects/property.py
potion/objects/query.py
potion/objects/rich.py
potion/objects/schema.py
potion/objects/user.py
potion/render/__init__.py
potion/render/base.py
potion/render/html.py
potion/render/markdown.py
potion/render/raw.py
potion/urls/__init__.py
potion/urls/v1.py
potion/utils/__init__.py
potion/utils/parser.py
potion/utils/req.py
notion_potion-0.2.2.dist-info/LICENSE
notion_potion-0.2.2.dist-info/METADATA
notion_potion-0.2.2.dist-info/WHEEL
notion_potion-0.2.2.dist-info/top_level.txt
notion_potion-0.2.2.dist-info/RECORD
