Metadata-Version: 2.1
Name: notion-potion
Version: 0.2.2
Summary: A functional, easy to use Python wrapper of Notion Api.
Home-page: https://github.com/sailist/potion
Author: sailist
Author-email: sailist@outlook.com
License: Apache License 2.0
Keywords: potion notion
Classifier: Programming Language :: Python :: 3
Classifier: Programming Language :: Python :: 3.6
Classifier: Programming Language :: Python :: 3.7
Classifier: Programming Language :: Python :: 3.8
Classifier: Programming Language :: Python :: 3.9
Classifier: Operating System :: OS Independent
Classifier: License :: OSI Approved :: GNU General Public License v3 (GPLv3)
License-File: LICENSE
Requires-Dist: dbrecord
Requires-Dist: requests
